LGTVController/__init__.py
LGTVController/endpoints.json
LGTVController/handshake.json
LGTVController-0.0.2.dist-info/METADATA
LGTVController-0.0.2.dist-info/WHEEL
LGTVController-0.0.2.dist-info/top_level.txt
LGTVController-0.0.2.dist-info/RECORD
