Metadata-Version: 2.1
Name: LGTVController
Version: 0.0.2
Summary: LG TV Controller
Home-page: https://github.com/48723247842/LGTVController
Author: 7435171
Author-email: 48723247842@protonmail.com
License: UNKNOWN
Platform: UNKNOWN
Classifier: Programming Language :: Python :: 3
Classifier: License :: OSI Approved :: MIT License
Classifier: Operating System :: OS Independent
Requires-Python: >=3.6
Requires-Dist: python-box (==6.0.2)
Requires-Dist: stackprinter (==0.2.6)
Requires-Dist: wakeonlan (==2.1.0)
Requires-Dist: websocket-client (==1.3.3)
